pyobjinfo.cpython-38-darwin.so
pyobjinfo-1.0.dist-info/LICENCE
pyobjinfo-1.0.dist-info/METADATA
pyobjinfo-1.0.dist-info/WHEEL
pyobjinfo-1.0.dist-info/top_level.txt
pyobjinfo-1.0.dist-info/RECORD
