Metadata-Version: 2.1
Name: pyobjinfo
Version: 1.0
Summary: Provides stats info about PyObject
Author: Vladas Tamošaitis
Author-email: amd.vladas@gmail.com
License: MIT
Platform: UNKNOWN
License-File: LICENCE
